{"cameraMode":{"drawMode":0,"name":"Shaded","section":"Shading Mode"},"sceneLighting":true,"audioPlay":false,"sceneViewState":{"m_AlwaysRefresh":false,"showFog":true,"showSkybox":true,"showFlares":true,"showImageEffects":true,"showParticleSystems":true,"showVisualEffectGraphs":true,"m_FxEnabled":true},"in2DMode":false,"pivot":{"x":0.6282144784927368,"y":-0.3314070403575897,"z":1.0778357982635499},"rotation":{"x":0.1033116802573204,"y":-0.00895086582750082,"z":0.0009317625663243234,"w":0.9946140646934509},"size":2.98000168800354,"orthographic":false}